exotic_bikes/__init__.py
exotic_bikes-0.1.0.dist-info/WHEEL
exotic_bikes-0.1.0.dist-info/entry_points.txt
exotic_bikes-0.1.0.dist-info/METADATA
exotic_bikes-0.1.0.dist-info/RECORD
