Metadata-Version: 2.3
Name: exotic-bikes
Version: 0.1.0
Summary: Add your description here
Author: Sid Anand
Author-email: Sid Anand <Sid.Anand@walmart.com>
Requires-Dist: requests>=2.32.5
Requires-Python: >=3.10
